[
    [
        {
            "quenya": "alda",
            "type": "сущ.",
            "ru": "дерево"
        },
        {
            "quenya": "ar",
            "type": "со.",
            "ru": "и"
        },
        {
            "quenya": "aran",
            "type": "сущ.",
            "ru": "король"
        },
        {
            "quenya": "ata",
            "type": "нареч.",
            "ru": "снова, опять"
        },
        {
            "quenya": "cen-",
            "type": "гл.",
            "ru": "видеть"
        },
        {
            "quenya": "hauta-",
            "type": "гл.",
            "ru": "останавливать"
        },
        {
            "quenya": "hilya-",
            "type": "гл.",
            "ru": "следовать, преследовать"
        },
        {
            "quenya": "imbë",
            "type": "предл.",
            "ru": "между"
        },
        {
            "quenya": "lambë",
            "type": "сущ.",
            "ru": "язык"
        },
        {
            "quenya": "lanta-",
            "type": "гл.",
            "ru": "падать"
        },
        {
            "quenya": "lassë",
            "type": "сущ.",
            "ru": "лист"
        },
        {
            "quenya": "lelya-",
            "type": "гл.",
            "ru": "идти, ходить, путешествовать"
        },
        {
            "quenya": "lómin",
            "type": "сущ.",
            "ru": "тень"
        },
        {
            "quenya": "má",
            "type": "сущ.",
            "ru": "рука (кисть руки)"
        },
        {
            "quenya": "mallë (мн.: maller)",
            "type": "сущ.",
            "ru": "дорога, улица"
        },
        {
            "quenya": "man?",
            "type": "",
            "ru": "кто? что?"
        },
        {
            "quenya": "mára",
            "type": "",
            "ru": "хороший, хорошо"
        },
        {
            "quenya": "massë?",
            "type": "",
            "ru": "где?"
        },
        {
            "quenya": "meldo",
            "type": "сущ.",
            "ru": "друг"
        },
        {
            "quenya": "mer-",
            "type": "гл.",
            "ru": "хотеть, желать"
        },
        {
            "quenya": "Namárië!",
            "type": "",
            "ru": "До свидания!"
        },
        {
            "quenya": "nilmë",
            "type": "сущ.",
            "ru": "дружба"
        },
        {
            "quenya": "nér (ner-)",
            "type": "сущ.",
            "ru": "мужчина"
        },
        {
            "quenya": "nu",
            "type": "предл.",
            "ru": "под"
        },
        {
            "quenya": "ora-",
            "type": "гл.",
            "ru": "призывать, побуждать"
        },
        {
            "quenya": "pol-",
            "type": "гл.",
            "ru": "мочь, иметь возможность"
        },
        {
            "quenya": "quet-",
            "type": "гл.",
            "ru": "говорить"
        },
        {
            "quenya": "ranco (мн.: ranqui)",
            "type": "сущ.",
            "ru": "рука (вся, от плеча)"
        },
        {
            "quenya": "sinomë",
            "type": "нареч.",
            "ru": "здесь, тут, сюда"
        },
        {
            "quenya": "tári",
            "type": "сущ.",
            "ru": "королева"
        },
        {
            "quenya": "taurë",
            "type": "сущ.",
            "ru": "лес"
        },
        {
            "quenya": "tië",
            "type": "сущ.",
            "ru": "путь, дорога"
        },
        {
            "quenya": "tir-",
            "type": "гл.",
            "ru": "охранять, наблюдать, стеречь, следить"
        },
        {
            "quenya": "tul-",
            "type": "гл.",
            "ru": "приходить"
        }
    ],
    [
        {
            "quenya": "ailin",
            "type": "сущ.",
            "ru": "озеро"
        },
        {
            "quenya": "aiwë",
            "type": "сущ.",
            "ru": "(небольшая) птица"
        },
        {
            "quenya": "ando",
            "type": "сущ.",
            "ru": "ворота"
        },
        {
            "quenya": "Anar",
            "type": "сущ.",
            "ru": "солнце"
        },
        {
            "quenya": "anda",
            "type": "прилаг.",
            "ru": "длинный"
        },
        {
            "quenya": "andúnë",
            "type": "сущ.",
            "ru": "вечер, закат"
        },
        {
            "quenya": "calima",
            "type": "прилаг.",
            "ru": "яркий, светлый"
        },
        {
            "quenya": "casar",
            "type": "сущ.",
            "ru": "гном"
        },
        {
            "quenya": "elda",
            "type": "сущ.",
            "ru": "эльф"
        },
        {
            "quenya": "hen (hend-)",
            "type": "сущ.",
            "ru": "глаз"
        },
        {
            "quenya": "hísië",
            "type": "сущ.",
            "ru": "мгла, сумерки"
        },
        {
            "quenya": "hísë",
            "type": "сущ.",
            "ru": "туман"
        },
        {
            "quenya": "ilya",
            "type": "сущ.",
            "ru": "каждый, весь"
        },
        {
            "quenya": "laica",
            "type": "прилаг.",
            "ru": "зелёный"
        },
        {
            "quenya": "laurëa",
            "type": "прилаг.",
            "ru": "золотистый"
        },
        {
            "quenya": "linta",
            "type": "прилаг.",
            "ru": "быстрый"
        },
        {
            "quenya": "linyenwa",
            "type": "прилаг.",
            "ru": "старый"
        },
        {
            "quenya": "maica",
            "type": "прилаг.",
            "ru": "острый"
        },
        {
            "quenya": "maita",
            "type": "прилаг.",
            "ru": "голодный"
        },
        {
            "quenya": "már",
            "type": "сущ.",
            "ru": "дом, родина, место жительства"
        },
        {
            "quenya": "melin",
            "type": "прилаг.",
            "ru": "любимый, дорогой"
        },
        {
            "quenya": "metta",
            "type": "сущ.",
            "ru": "конец"
        },
        {
            "quenya": "Mithrimessë",
            "type": "сущ.",
            "ru": "[на озере] Митрим"
        },
        {
            "quenya": "morë",
            "type": "прилаг.",
            "ru": "тёмный, чёрный"
        },
        {
            "quenya": "na",
            "type": "предл.",
            "ru": "в, на, к"
        },
        {
            "quenya": "nan",
            "type": "со.",
            "ru": "но, однако, всё же"
        },
        {
            "quenya": "nat",
            "type": "сущ.",
            "ru": "вещь"
        },
        {
            "quenya": "Noldoiva",
            "type": "сущ.",
            "ru": "[принадлежащий] нолдор"
        },
        {
            "quenya": "nórë",
            "type": "сущ.",
            "ru": "местность"
        },
        {
            "quenya": "norno",
            "type": "сущ.",
            "ru": "дуб"
        },
        {
            "quenya": "núta-",
            "type": "гл.",
            "ru": "садиться, заходить (о солнце и луне)"
        },
        {
            "quenya": "orco",
            "type": "сущ.",
            "ru": "орк"
        },
        {
            "quenya": "oron (oront-)",
            "type": "сущ.",
            "ru": "гора"
        },
        {
            "quenya": "osto",
            "type": "сущ.",
            "ru": "крепость, город"
        },
        {
            "quenya": "pé (pe-)",
            "type": "сущ.",
            "ru": "губа"
        },
        {
            "quenya": "ranya-",
            "type": "сущ.",
            "ru": "бродить, блуждать"
        },
        {
            "quenya": "rimba",
            "type": "сущ.",
            "ru": "частый, многий, многочисленный"
        },
        {
            "quenya": "ringa",
            "type": "прилаг.",
            "ru": "холодный"
        },
        {
            "quenya": "sil-",
            "type": "гл.",
            "ru": "светить, сиять"
        },
        {
            "quenya": "tál (tal-)",
            "type": "сущ.",
            "ru": "ступня"
        },
        {
            "quenya": "tára",
            "type": "прилаг.",
            "ru": "высокий"
        },
        {
            "quenya": "telco (мн. telqui)",
            "type": "сущ.",
            "ru": "нога, ножка"
        },
        {
            "quenya": "terë",
            "type": "предл.",
            "ru": "через, сквозь"
        },
        {
            "quenya": "tulca",
            "type": "прилаг.",
            "ru": "сильный"
        },
        {
            "quenya": "vanya",
            "type": "прилаг.",
            "ru": "красивый"
        },
        {
            "quenya": "wil-",
            "type": "гл.",
            "ru": "летать"
        }
    ],
    [
        {
            "quenya": "alcar",
            "type": "сущ.",
            "ru": "слава; блеск, великолепие"
        },
        {
            "quenya": "alta",
            "type": "прилаг.",
            "ru": "большой, огромный"
        },
        {
            "quenya": "anga",
            "type": "сущ.",
            "ru": "железо"
        },
        {
            "quenya": "calma",
            "type": "сущ.",
            "ru": "лампа, светильник"
        },
        {
            "quenya": "cirya",
            "type": "сущ.",
            "ru": "корабль"
        },
        {
            "quenya": "coa",
            "type": "сущ.",
            "ru": "дом, здание"
        },
        {
            "quenya": "cuilë",
            "type": "сущ.",
            "ru": "жизнь"
        },
        {
            "quenya": "elen",
            "type": "сущ.",
            "ru": "звезда"
        },
        {
            "quenya": "faina-",
            "type": "гл.",
            "ru": "испускать свет"
        },
        {
            "quenya": "heru",
            "type": "сущ.",
            "ru": "господин, хозяин, повелитель, глава, начальник, командир"
        },
        {
            "quenya": "indis",
            "type": "сущ.",
            "ru": "невеста"
        },
        {
            "quenya": "láta",
            "type": "прилаг.",
            "ru": "распахнутый"
        },
        {
            "quenya": "macil",
            "type": "сущ.",
            "ru": "меч"
        },
        {
            "quenya": "mi",
            "type": "предл.",
            "ru": "в [чём-то]"
        },
        {
            "quenya": "mindon",
            "type": "сущ.",
            "ru": "башня"
        },
        {
            "quenya": "mól",
            "type": "сущ.",
            "ru": "раб"
        },
        {
            "quenya": "mornië",
            "type": "сущ.",
            "ru": "тьма"
        },
        {
            "quenya": "ohtar",
            "type": "сущ.",
            "ru": "воин, солдат"
        },
        {
            "quenya": "ondo",
            "type": "сущ.",
            "ru": "камень (как материал), скала"
        },
        {
            "quenya": "quenta",
            "type": "сущ.",
            "ru": "рассказ, история"
        },
        {
            "quenya": "ramba",
            "type": "сущ.",
            "ru": "стена"
        },
        {
            "quenya": "sar (sard-)",
            "type": "сущ.",
            "ru": "камень (одиночный)"
        },
        {
            "quenya": "taura",
            "type": "прилаг.",
            "ru": "могущественный"
        },
        {
            "quenya": "telpë",
            "type": "сущ.",
            "ru": "серебро"
        },
        {
            "quenya": "telpina",
            "type": "прилаг.",
            "ru": "серебряный"
        },
        {
            "quenya": "toa",
            "type": "сущ.",
            "ru": "дерево, древесина"
        },
        {
            "quenya": "varya-",
            "type": "гл.",
            "ru": "защищать"
        },
        {
            "quenya": "vinya",
            "type": "прилаг.",
            "ru": "новый"
        },
        {
            "quenya": "yendë",
            "type": "сущ.",
            "ru": "дочь"
        }
    ],
    [
        {
            "quenya": "cap-",
            "type": "гл.",
            "ru": "прыгать"
        },
        {
            "quenya": "car-",
            "type": "гл.",
            "ru": "делать"
        },
        {
            "quenya": "cotumo",
            "type": "сущ.",
            "ru": "враг"
        },
        {
            "quenya": "epë",
            "type": "предл.",
            "ru": "до, перед"
        },
        {
            "quenya": "farya-",
            "type": "гл.",
            "ru": "быть достаточным"
        },
        {
            "quenya": "lasta-",
            "type": "гл.",
            "ru": "слушать"
        },
        {
            "quenya": "limpë",
            "type": "сущ.",
            "ru": "вино"
        },
        {
            "quenya": "mahta-",
            "type": "гл.",
            "ru": "сражаться"
        },
        {
            "quenya": "mapa-",
            "type": "гл.",
            "ru": "брать, хватать"
        },
        {
            "quenya": "nyar-",
            "type": "гл.",
            "ru": "рассказывать"
        },
        {
            "quenya": "senda",
            "type": "прилаг.",
            "ru": "мирный"
        },
        {
            "quenya": "tec-",
            "type": "гл.",
            "ru": "писать"
        },
        {
            "quenya": "tielyanna",
            "type": "",
            "ru": "на Ваш путь"
        },
        {
            "quenya": "yulma",
            "type": "сущ.",
            "ru": "чаша"
        }
    ],
    [
        {
            "quenya": "alta",
            "type": "прилаг.",
            "ru": "большой, огромный"
        },
        {
            "quenya": "arda",
            "type": "сущ.",
            "ru": "страна, область"
        },
        {
            "quenya": "caita-",
            "type": "гл.",
            "ru": "лежать"
        },
        {
            "quenya": "cala",
            "type": "сущ.",
            "ru": "свет"
        },
        {
            "quenya": "callo",
            "type": "сущ.",
            "ru": "герой"
        },
        {
            "quenya": "cú",
            "type": "сущ.",
            "ru": "лук, дуга, полумесяц"
        },
        {
            "quenya": "cuivë",
            "type": "сущ.",
            "ru": "пробуждение"
        },
        {
            "quenya": "ehtë",
            "type": "сущ.",
            "ru": "копьё"
        },
        {
            "quenya": "harya-",
            "type": "гл.",
            "ru": "иметь, владеть, обладать"
        },
        {
            "quenya": "hir-",
            "type": "гл.",
            "ru": "находить"
        },
        {
            "quenya": "huinë",
            "type": "сущ.",
            "ru": "мрак, тьма"
        },
        {
            "quenya": "ista-",
            "type": "гл.",
            "ru": "знать"
        },
        {
            "quenya": "linda-",
            "type": "гл.",
            "ru": "петь"
        },
        {
            "quenya": "mar-",
            "type": "гл.",
            "ru": "жить, пребывать, проживать; ждать"
        },
        {
            "quenya": "mel-",
            "type": "гл.",
            "ru": "любить"
        },
        {
            "quenya": "nauco",
            "type": "сущ.",
            "ru": "гном"
        },
        {
            "quenya": "ohta",
            "type": "сущ.",
            "ru": "война"
        },
        {
            "quenya": "olor",
            "type": "сущ.",
            "ru": "сновидение, мечта"
        },
        {
            "quenya": "palla",
            "type": "прилаг.",
            "ru": "широкий, обширный"
        },
        {
            "quenya": "pusta-",
            "type": "гл.",
            "ru": "переставать, прекращать"
        },
        {
            "quenya": "saila",
            "type": "гл.",
            "ru": "мудрый, мудрец"
        },
        {
            "quenya": "sérë",
            "type": "сущ.",
            "ru": "мир (т.е. не война)"
        },
        {
            "quenya": "sinta (th-)",
            "type": "прилаг.",
            "ru": "короткий, краткий"
        },
        {
            "quenya": "tanca",
            "type": "прилаг.",
            "ru": "уверенный"
        },
        {
            "quenya": "tur-",
            "type": "гл.",
            "ru": "уметь, владеть навыком, управлять"
        },
        {
            "quenya": "úmëa",
            "type": "прилаг.",
            "ru": "злой, плохой"
        },
        {
            "quenya": "vanwa",
            "type": "прилаг.",
            "ru": "ушедший, утерянный, утраченный"
        }
    ],
    [
        {
            "quenya": "alarca",
            "type": "прилаг.",
            "ru": "быстрый, спешный"
        },
        {
            "quenya": "alasaila",
            "type": "прилаг.",
            "ru": "не(благо)разумный"
        },
        {
            "quenya": "aurë",
            "type": "сущ.",
            "ru": "день"
        },
        {
            "quenya": "en-",
            "type": "приставка",
            "ru": "вновь"
        },
        {
            "quenya": "erë",
            "type": "сущ.",
            "ru": "сталь"
        },
        {
            "quenya": "fir-",
            "type": "гл.",
            "ru": "умирать"
        },
        {
            "quenya": "Formen",
            "type": "сущ.",
            "ru": "север"
        },
        {
            "quenya": "hilyala",
            "type": "сущ.",
            "ru": "следующий"
        },
        {
            "quenya": "Hyarmen",
            "type": "сущ.",
            "ru": "юг"
        },
        {
            "quenya": "Isil",
            "type": "сущ.",
            "ru": "луна"
        },
        {
            "quenya": "lamma",
            "type": "сущ.",
            "ru": "звук"
        },
        {
            "quenya": "lúme",
            "type": "сущ.",
            "ru": "час, время"
        },
        {
            "quenya": "mahtalë",
            "type": "сущ.",
            "ru": "бой, сражение"
        },
        {
            "quenya": "nóme",
            "type": "сущ.",
            "ru": "место"
        },
        {
            "quenya": "Númen",
            "type": "сущ.",
            "ru": "запад"
        },
        {
            "quenya": "quen",
            "type": "местоим.",
            "ru": "кто-то, кто-либо, некто"
        },
        {
            "quenya": "Rómen",
            "type": "сущ.",
            "ru": "восток"
        },
        {
            "quenya": "sercë",
            "type": "сущ.",
            "ru": "кровь"
        },
        {
            "quenya": "talan (talam-)",
            "type": "сущ.",
            "ru": "пол, этаж, ярус, здесь: земля"
        },
        {
            "quenya": "tinco",
            "type": "сущ.",
            "ru": "металл"
        },
        {
            "quenya": "toron (torn-)",
            "type": "сущ.",
            "ru": "брат"
        },
        {
            "quenya": "yondo",
            "type": "сущ.",
            "ru": "сын"
        }
    ]
]